LICENSE
MANIFEST.in
README.md
setup.py
kartfire/ActionEmail.py
kartfire/ActionMerge.py
kartfire/ActionReference.py
kartfire/ActionRender.py
kartfire/ActionRun.py
kartfire/BaseAction.py
kartfire/CmdlineEscape.py
kartfire/Docker.py
kartfire/Enums.py
kartfire/Exceptions.py
kartfire/FriendlyArgumentParser.py
kartfire/MultiCommand.py
kartfire/PrefixMatcher.py
kartfire/StateFile.py
kartfire/Submission.py
kartfire/SubmissionEvaluation.py
kartfire/TestFixtureConfig.py
kartfire/TestbatchEvaluation.py
kartfire/Testcase.py
kartfire/TestcaseCollection.py
kartfire/TestcaseRunner.py
kartfire/TestrunnerOutput.py
kartfire/Tools.py
kartfire/__init__.py
kartfire/__main__.py
kartfire.egg-info/PKG-INFO
kartfire.egg-info/SOURCES.txt
kartfire.egg-info/dependency_links.txt
kartfire.egg-info/entry_points.txt
kartfire.egg-info/top_level.txt
kartfire/container/container_testrunner