Metadata-Version: 2.1
Name: kartfire
Version: 0.0.6
Summary: Toolkit to perform known-answer testing in Docker-isolated environments
Home-page: https://github.com/johndoe31415/kartfire
Download-URL: https://github.com/johndoe31415/kartfire/archive/v0.0.6.tar.gz
Author: Johannes Bauer
Author-email: joe@johannes-bauer.com
License: gpl-3.0
Keywords: testcase,runner,docker
Classifier: Development Status :: 5 - Production/Stable
Classifier: Intended Audience :: Developers
Classifier: License :: OSI Approved :: GNU General Public License v3 (GPLv3)
Classifier: Programming Language :: Python :: 3
Classifier: Programming Language :: Python :: 3 :: Only
Classifier: Programming Language :: Python :: 3.10
License-File: LICENSE
